{
  "books": [
    {
      "title": "Мастер и Маргарита",
      "author": "Михаил Булгаков",
      "reting": null,
      "description" : null
    },
    {
      "title": "Сексус-Плексус-Нексус",
      "author": "Генри Миллер",
      "reting": null,
      "description" : null
    },
    {
      "title": "Три товарища",
      "author": "Эрих Мария Ремарк",
      "reting": null,
      "description" : null
    },
    {
      "title": "По ком звонит колокол",
      "author": "Эрнест Хэмингуэей",
      "reting": null,
      "description" : null
    },
    {
      "title": "Прощай, Оружие",
      "author": "Эрнест Хэмингуэей",
      "reting": null,
      "description" : null
    },
    {
      "title": "Старик и море",
      "author": "Эрнест Хэмингуэей",
      "reting": null,
      "description" : null
    },
    {
      "title": "Охота на овец",
      "author": "Харуки Мураками",
      "reting": null,
      "description" : null
    },
    {
      "title": "Dance Dance Dance",
      "author": "Харуки Мураками",
      "reting": null,
      "description" : null
    },
    {
      "title": "О чем я говорю, когда говорю о беге",
      "author": "Харуки Мураками",
      "reting": null,
      "description" : null
    },
    {
      "title": "Капитанская дочка",
      "author": "Александр Пушкин",
      "reting": null,
      "description" : null
    },
    {
      "title": "Пикник на обочине",
      "author": "Аркадий и Борис Стругацкие",
      "reting": null,
      "description" : null
    },
    {
      "title": "Трудно быть богом",
      "author": "Аркадий и Борис Стругацкие",
      "reting": null,
      "description" : null
    },
    {
      "title": "За миллиард лет до конца света",
      "author": "Аркадий и Борис Стругацкие",
      "reting": null,
      "description" : null
    },
    {
      "title": "Лабиринт Отражений",
      "author": "Сергей Лукьяненко",
      "reting": null,
      "description" : null
    },
    {
      "title": "Кривые зеркала",
      "author": "Сергей Лукьяненко",
      "reting": null,
      "description" : null
    },
    {
      "title": "Я, Робот",
      "author": "Айзек Азимов",
      "reting": null,
      "description" : null
    },
    {
      "title": "451 по Фаренгейту",
      "author": "Рей Бредбери",
      "reting": null,
      "description" : null
    },
    {
      "title": "Марсианские хроники",
      "author": "Рей Бредбери",
      "reting": null,
      "description" : null
    },
    {
      "title": "SAPIENS",
      "author": "Ной Юваль Харари",
      "reting": null,
      "description" : null
    },
    {
      "title": "Думай медленно, решай быстро",
      "author": "Даниел Канеман",
      "reting": null,
      "description" : null
    },
    {
      "title": "Физика невозможного",
      "author": "Митио Каку",
      "reting": 8.0,
      "description" : null
    },
    {
      "title": "Вы наверное шутите, мистер Фейнман",
      "author": "Ричард Фейнман ",
      "reting": 8.0,
      "description" : null
    },
    {
      "title": "Как писать книги",
      "author": "Стивен Кинг",
      "reting": null,
      "description" : null
    },
    {
      "title": "Выходные всю неделю",
      "author": "Рикардо Семлер",
      "reting": null,
      "description" : null
    },
    {
      "title": "Homo Deus",
      "author": "Ной Юваль Харари",
      "reting": null,
      "description" : null
    },
    {
      "title": "Джим Стальная Крыса",
      "author": "Гарри Гарсон",
      "reting": null,
      "description" : null
    },
    {
      "title": "Ариель",
      "author": "Александр Беляев",
      "reting": null,
      "description" : null
    },
    {
      "title": "Человек-Амфибия",
      "author": "Александр Беляев",
      "reting": null,
      "description" : null
    },
    {
      "title": "Гиперболоид Инженера Гарина",
      "author": "Александр Беляев",
      "reting": null,
      "description" : null
    },
    {
      "title": "Чиполино",
      "author": "Драни Радари",
      "reting": null,
      "description" : null
    },
    {
      "title": "Третья Экспедиция",
      "author": "Рэй Бредбери",
      "reting": null,
      "description" : null
    },
    {
      "title": "Дом на краю света",
      "author": "Майкл Каннингем",
      "reting": null,
      "description" : null
    },
    {
      "title": "Богач, бедняк",
      "author": "Ирвин Шоу",
      "reting": null,
      "description" : null
    },
    {
      "title": "Шантарам",
      "author": "Грегори Робертс",
      "reting": null,
      "description" : null
    },
    {
      "title": "Криптономикон",
      "author": "Нил Стивенсон",
      "reting": null,
      "description" : null
    },
    {
      "title": "По ту сторону добра и зла",
      "author": "Фридрих Ницше",
      "reting": null,
      "description" : null
    },
    {
      "title": "Поднятая целина",
      "author": "Михаил Шолохов",
      "reting": null,
      "description" : null
    },
    {
      "title": "Крайняя битва чекистов с масонами",
      "author": "Виктор Пелевин",
      "reting": null,
      "description" : null
    },
    {
      "title": "20000 лье под водой",
      "author": "Жюль Верн",
      "reting": null,
      "description" : null
    },
    {
      "title": "Незнайка, Незнайка на Луне",
      "author": "Николай Носов",
      "reting": null,
      "description" : null
    },
    {
      "title": "Лед номер 9 (Колыбель для кошки)",
      "author": "Курт Воннегут",
      "reting": null,
      "description" : null
    },
    {
      "title": "Звездный десант",
      "author": "Роберт Хайнлайн",
      "reting": null,
      "description" : null
    },
    {
      "title": "Идиот",
      "author": "Федор Достоевский",
      "reting": null,
      "description" : null
    },
    {
      "title": "Рассказы",
      "author": "Чехов",
      "reting": null,
      "description" : null
    },
    {
      "title": "Полное собрание сочинений",
      "author": "Сергей Довлатов",
      "reting": null,
      "description" : null
    },
    {
      "title": "Автостопом по галактике",
      "author": "Дуглас Адамс",
      "reting": null,
      "description" : null
    },
    {
      "title": "Тайный дневник девушки по вызову",
      "author": "Бель дю жур",
      "reting": null,
      "description" : null
    },
    {
      "title": "Мертвые души",
      "author": "Николай Гоголь",
      "reting": null,
      "description" : null
    },
    {
      "title": "Вечера на хуторе близ Диканьки",
      "author": "Николай Гоголь",
      "reting": null,
      "description" : null
    },
    {
      "title": "Над пропастью во ржи",
      "author": "Джером Селинжер",
      "reting": null,
      "description" : null
    },
    {
      "title": "Гамлет",
      "author": "Уильям Шекспир",
      "reting": null,
      "description" : null
    },
    {
      "title": "Ромео и Джульетта",
      "author": "Уильям Шекспир",
      "reting": null,
      "description" : null
    },
    {
      "title": "Розенкранц и Гильденстерн мертвы",
      "author": "Том Стоппард",
      "reting": null,
      "description" : null
    },
    {
      "title": "Изображая жертву",
      "author": "Братья Пресняковы",
      "reting": null,
      "description" : null
    }
  ]
}
